{
  "summary": {
    "generated_at": "2026-05-11T11:25:47Z",
    "base_url": "https://fadhil.dev",
    "duplicate_groups_total": 35,
    "elapsed_seconds": 4.91
  },
  "domain": {
    "summary": {
      "paths_checked": 13,
      "http_200_count": 13,
      "redirect_count": 0,
      "error_count": 0,
      "missing_meta_description_count": 0,
      "missing_canonical_count": 0,
      "missing_h1_count": 0,
      "missing_html_lang_count": 0,
      "missing_og_title_count": 0,
      "missing_og_description_count": 0,
      "missing_twitter_card_count": 0,
      "missing_json_ld_count": 0,
      "non_https_final_count": 0,
      "avg_response_time_ms": 100.7,
      "p95_response_time_ms": 142.1,
      "max_response_time_ms": 159.7,
      "missing_security_headers_count": 0,
      "missing_security_header_details": {
        "content-security-policy": 0,
        "strict-transport-security": 0,
        "x-content-type-options": 0,
        "referrer-policy": 0
      }
    },
    "results": [
      {
        "path": "/",
        "url": "https://fadhil.dev/",
        "status": 200,
        "time_ms": 92.4,
        "final_url": "https://fadhil.dev/",
        "final_path": "/",
        "is_https_final": true,
        "redirected": false,
        "redirect_target": "",
        "content_type": "text/html; charset=utf-8",
        "content_length": 0,
        "cache_control": "public, max-age=0, must-revalidate, s-maxage=60, stale-while-revalidate=300",
        "security_headers": {
          "content-security-policy": true,
          "strict-transport-security": true,
          "x-content-type-options": true,
          "referrer-policy": true
        },
        "title": "Fadhil Akbar Cariearsa | Generalist & Student of the Craft",
        "seo_basics": {
          "meta_description": true,
          "canonical": true,
          "canonical_href": "https://fadhil.dev/",
          "has_h1": true,
          "noindex": false,
          "html_lang": true,
          "og_title": true,
          "og_description": true,
          "twitter_card": true,
          "json_ld": true
        },
        "processing_hints": {
          "script_tags": 4,
          "stylesheet_links": 1
        },
        "deprecated_flags": [],
        "worker_policy_enforced": true
      },
      {
        "path": "/archives",
        "url": "https://fadhil.dev/archives",
        "status": 200,
        "time_ms": 87.2,
        "final_url": "https://fadhil.dev/archives",
        "final_path": "/archives",
        "is_https_final": true,
        "redirected": false,
        "redirect_target": "",
        "content_type": "text/html; charset=utf-8",
        "content_length": 0,
        "cache_control": "public, max-age=0, must-revalidate, s-maxage=60, stale-while-revalidate=300",
        "security_headers": {
          "content-security-policy": true,
          "strict-transport-security": true,
          "x-content-type-options": true,
          "referrer-policy": true
        },
        "title": "Fadhil Akbar Cariearsa | Generalist & Student of the Craft",
        "seo_basics": {
          "meta_description": true,
          "canonical": true,
          "canonical_href": "https://fadhil.dev/archives",
          "has_h1": true,
          "noindex": false,
          "html_lang": true,
          "og_title": true,
          "og_description": true,
          "twitter_card": true,
          "json_ld": true
        },
        "processing_hints": {
          "script_tags": 3,
          "stylesheet_links": 1
        },
        "deprecated_flags": [],
        "worker_policy_enforced": true
      },
      {
        "path": "/books",
        "url": "https://fadhil.dev/books",
        "status": 200,
        "time_ms": 114.2,
        "final_url": "https://fadhil.dev/books",
        "final_path": "/books",
        "is_https_final": true,
        "redirected": false,
        "redirect_target": "",
        "content_type": "text/html; charset=utf-8",
        "content_length": 0,
        "cache_control": "public, max-age=0, must-revalidate, s-maxage=60, stale-while-revalidate=300",
        "security_headers": {
          "content-security-policy": true,
          "strict-transport-security": true,
          "x-content-type-options": true,
          "referrer-policy": true
        },
        "title": "Fadhil Akbar Cariearsa | Generalist & Student of the Craft",
        "seo_basics": {
          "meta_description": true,
          "canonical": true,
          "canonical_href": "https://fadhil.dev/books",
          "has_h1": true,
          "noindex": false,
          "html_lang": true,
          "og_title": true,
          "og_description": true,
          "twitter_card": true,
          "json_ld": true
        },
        "processing_hints": {
          "script_tags": 3,
          "stylesheet_links": 1
        },
        "deprecated_flags": [],
        "worker_policy_enforced": true
      },
      {
        "path": "/books/editor",
        "url": "https://fadhil.dev/books/editor",
        "status": 200,
        "time_ms": 159.7,
        "final_url": "https://fadhil.dev/books/editor",
        "final_path": "/books/editor",
        "is_https_final": true,
        "redirected": false,
        "redirect_target": "",
        "content_type": "text/html; charset=utf-8",
        "content_length": 0,
        "cache_control": "public, max-age=0, must-revalidate, s-maxage=60, stale-while-revalidate=300",
        "security_headers": {
          "content-security-policy": true,
          "strict-transport-security": true,
          "x-content-type-options": true,
          "referrer-policy": true
        },
        "title": "Fadhil Akbar Cariearsa | Generalist & Student of the Craft",
        "seo_basics": {
          "meta_description": true,
          "canonical": true,
          "canonical_href": "https://fadhil.dev/books/editor",
          "has_h1": true,
          "noindex": false,
          "html_lang": true,
          "og_title": true,
          "og_description": true,
          "twitter_card": true,
          "json_ld": true
        },
        "processing_hints": {
          "script_tags": 3,
          "stylesheet_links": 1
        },
        "deprecated_flags": [],
        "worker_policy_enforced": true
      },
      {
        "path": "/daily-streak",
        "url": "https://fadhil.dev/daily-streak",
        "status": 200,
        "time_ms": 120.3,
        "final_url": "https://fadhil.dev/daily-streak",
        "final_path": "/daily-streak",
        "is_https_final": true,
        "redirected": false,
        "redirect_target": "",
        "content_type": "text/html; charset=utf-8",
        "content_length": 0,
        "cache_control": "public, max-age=0, must-revalidate, s-maxage=60, stale-while-revalidate=300",
        "security_headers": {
          "content-security-policy": true,
          "strict-transport-security": true,
          "x-content-type-options": true,
          "referrer-policy": true
        },
        "title": "Daily Streak Checklist",
        "seo_basics": {
          "meta_description": true,
          "canonical": true,
          "canonical_href": "https://fadhil.dev/website/daily-streak/index.html",
          "has_h1": true,
          "noindex": false,
          "html_lang": true,
          "og_title": true,
          "og_description": true,
          "twitter_card": true,
          "json_ld": true
        },
        "processing_hints": {
          "script_tags": 3,
          "stylesheet_links": 1
        },
        "deprecated_flags": [],
        "worker_policy_enforced": true
      },
      {
        "path": "/dreambusiness",
        "url": "https://fadhil.dev/dreambusiness",
        "status": 200,
        "time_ms": 142.1,
        "final_url": "https://fadhil.dev/dreambusiness",
        "final_path": "/dreambusiness",
        "is_https_final": true,
        "redirected": false,
        "redirect_target": "",
        "content_type": "text/html; charset=utf-8",
        "content_length": 0,
        "cache_control": "public, max-age=0, must-revalidate, s-maxage=60, stale-while-revalidate=300",
        "security_headers": {
          "content-security-policy": true,
          "strict-transport-security": true,
          "x-content-type-options": true,
          "referrer-policy": true
        },
        "title": "Fadhil Akbar Cariearsa | Generalist & Student of the Craft",
        "seo_basics": {
          "meta_description": true,
          "canonical": true,
          "canonical_href": "https://fadhil.dev/dreambusiness",
          "has_h1": true,
          "noindex": false,
          "html_lang": true,
          "og_title": true,
          "og_description": true,
          "twitter_card": true,
          "json_ld": true
        },
        "processing_hints": {
          "script_tags": 4,
          "stylesheet_links": 1
        },
        "deprecated_flags": [],
        "worker_policy_enforced": true
      },
      {
        "path": "/home",
        "url": "https://fadhil.dev/home",
        "status": 200,
        "time_ms": 123.4,
        "final_url": "https://fadhil.dev/home",
        "final_path": "/home",
        "is_https_final": true,
        "redirected": false,
        "redirect_target": "",
        "content_type": "text/html; charset=utf-8",
        "content_length": 0,
        "cache_control": "public, max-age=0, must-revalidate, s-maxage=60, stale-while-revalidate=300",
        "security_headers": {
          "content-security-policy": true,
          "strict-transport-security": true,
          "x-content-type-options": true,
          "referrer-policy": true
        },
        "title": "Fadhil Akbar Cariearsa | Generalist & Student of the Craft",
        "seo_basics": {
          "meta_description": true,
          "canonical": true,
          "canonical_href": "https://fadhil.dev/home",
          "has_h1": true,
          "noindex": false,
          "html_lang": true,
          "og_title": true,
          "og_description": true,
          "twitter_card": true,
          "json_ld": true
        },
        "processing_hints": {
          "script_tags": 2,
          "stylesheet_links": 2
        },
        "deprecated_flags": [],
        "worker_policy_enforced": true
      },
      {
        "path": "/hype",
        "url": "https://fadhil.dev/hype",
        "status": 200,
        "time_ms": 108.6,
        "final_url": "https://fadhil.dev/hype",
        "final_path": "/hype",
        "is_https_final": true,
        "redirected": false,
        "redirect_target": "",
        "content_type": "text/html; charset=utf-8",
        "content_length": 0,
        "cache_control": "public, max-age=0, must-revalidate, s-maxage=60, stale-while-revalidate=300",
        "security_headers": {
          "content-security-policy": true,
          "strict-transport-security": true,
          "x-content-type-options": true,
          "referrer-policy": true
        },
        "title": "Fadhil Akbar Cariearsa | Generalist & Student of the Craft",
        "seo_basics": {
          "meta_description": true,
          "canonical": true,
          "canonical_href": "https://fadhil.dev/hype",
          "has_h1": true,
          "noindex": false,
          "html_lang": true,
          "og_title": true,
          "og_description": true,
          "twitter_card": true,
          "json_ld": true
        },
        "processing_hints": {
          "script_tags": 3,
          "stylesheet_links": 1
        },
        "deprecated_flags": [],
        "worker_policy_enforced": true
      },
      {
        "path": "/mindmapmaker",
        "url": "https://fadhil.dev/mindmapmaker",
        "status": 200,
        "time_ms": 90.9,
        "final_url": "https://fadhil.dev/mindmapmaker",
        "final_path": "/mindmapmaker",
        "is_https_final": true,
        "redirected": false,
        "redirect_target": "",
        "content_type": "text/html; charset=utf-8",
        "content_length": 0,
        "cache_control": "public, max-age=0, must-revalidate, s-maxage=60, stale-while-revalidate=300",
        "security_headers": {
          "content-security-policy": true,
          "strict-transport-security": true,
          "x-content-type-options": true,
          "referrer-policy": true
        },
        "title": "Fadhil Akbar Cariearsa | Generalist & Student of the Craft",
        "seo_basics": {
          "meta_description": true,
          "canonical": true,
          "canonical_href": "https://fadhil.dev/mindmapmaker",
          "has_h1": true,
          "noindex": false,
          "html_lang": true,
          "og_title": true,
          "og_description": true,
          "twitter_card": true,
          "json_ld": true
        },
        "processing_hints": {
          "script_tags": 3,
          "stylesheet_links": 2
        },
        "deprecated_flags": [],
        "worker_policy_enforced": true
      },
      {
        "path": "/mindmapmaker/editor/1",
        "url": "https://fadhil.dev/mindmapmaker/editor/1",
        "status": 200,
        "time_ms": 68.2,
        "final_url": "https://fadhil.dev/mindmapmaker/editor/1",
        "final_path": "/mindmapmaker/editor/1",
        "is_https_final": true,
        "redirected": false,
        "redirect_target": "",
        "content_type": "text/html; charset=utf-8",
        "content_length": 0,
        "cache_control": "public, max-age=0, must-revalidate, s-maxage=60, stale-while-revalidate=300",
        "security_headers": {
          "content-security-policy": true,
          "strict-transport-security": true,
          "x-content-type-options": true,
          "referrer-policy": true
        },
        "title": "Fadhil Akbar Cariearsa | Generalist & Student of the Craft",
        "seo_basics": {
          "meta_description": true,
          "canonical": true,
          "canonical_href": "https://fadhil.dev/mindmapmaker/editor/1",
          "has_h1": true,
          "noindex": false,
          "html_lang": true,
          "og_title": true,
          "og_description": true,
          "twitter_card": true,
          "json_ld": true
        },
        "processing_hints": {
          "script_tags": 3,
          "stylesheet_links": 2
        },
        "deprecated_flags": [],
        "worker_policy_enforced": true
      },
      {
        "path": "/rpg",
        "url": "https://fadhil.dev/rpg",
        "status": 200,
        "time_ms": 94.9,
        "final_url": "https://fadhil.dev/rpg",
        "final_path": "/rpg",
        "is_https_final": true,
        "redirected": false,
        "redirect_target": "",
        "content_type": "text/html; charset=utf-8",
        "content_length": 0,
        "cache_control": "public, max-age=0, must-revalidate, s-maxage=60, stale-while-revalidate=300",
        "security_headers": {
          "content-security-policy": true,
          "strict-transport-security": true,
          "x-content-type-options": true,
          "referrer-policy": true
        },
        "title": "Fadhil Akbar Cariearsa | Generalist & Student of the Craft",
        "seo_basics": {
          "meta_description": true,
          "canonical": true,
          "canonical_href": "https://fadhil.dev/rpg",
          "has_h1": true,
          "noindex": false,
          "html_lang": true,
          "og_title": true,
          "og_description": true,
          "twitter_card": true,
          "json_ld": true
        },
        "processing_hints": {
          "script_tags": 5,
          "stylesheet_links": 0
        },
        "deprecated_flags": [],
        "worker_policy_enforced": true
      },
      {
        "path": "/shareideas",
        "url": "https://fadhil.dev/shareideas",
        "status": 200,
        "time_ms": 47.8,
        "final_url": "https://fadhil.dev/shareideas",
        "final_path": "/shareideas",
        "is_https_final": true,
        "redirected": false,
        "redirect_target": "",
        "content_type": "text/html; charset=utf-8",
        "content_length": 0,
        "cache_control": "public, max-age=0, must-revalidate, s-maxage=60, stale-while-revalidate=300",
        "security_headers": {
          "content-security-policy": true,
          "strict-transport-security": true,
          "x-content-type-options": true,
          "referrer-policy": true
        },
        "title": "Fadhil Akbar Cariearsa | Generalist & Student of the Craft",
        "seo_basics": {
          "meta_description": true,
          "canonical": true,
          "canonical_href": "https://fadhil.dev/shareideas",
          "has_h1": true,
          "noindex": false,
          "html_lang": true,
          "og_title": true,
          "og_description": true,
          "twitter_card": true,
          "json_ld": true
        },
        "processing_hints": {
          "script_tags": 3,
          "stylesheet_links": 1
        },
        "deprecated_flags": [],
        "worker_policy_enforced": true
      },
      {
        "path": "/shareideas/page/1",
        "url": "https://fadhil.dev/shareideas/page/1",
        "status": 200,
        "time_ms": 60.0,
        "final_url": "https://fadhil.dev/shareideas/page/1",
        "final_path": "/shareideas/page/1",
        "is_https_final": true,
        "redirected": false,
        "redirect_target": "",
        "content_type": "text/html; charset=utf-8",
        "content_length": 0,
        "cache_control": "public, max-age=0, must-revalidate, s-maxage=60, stale-while-revalidate=300",
        "security_headers": {
          "content-security-policy": true,
          "strict-transport-security": true,
          "x-content-type-options": true,
          "referrer-policy": true
        },
        "title": "Fadhil Akbar Cariearsa | Generalist & Student of the Craft",
        "seo_basics": {
          "meta_description": true,
          "canonical": true,
          "canonical_href": "https://fadhil.dev/shareideas/page/1",
          "has_h1": true,
          "noindex": false,
          "html_lang": true,
          "og_title": true,
          "og_description": true,
          "twitter_card": true,
          "json_ld": true
        },
        "processing_hints": {
          "script_tags": 3,
          "stylesheet_links": 1
        },
        "deprecated_flags": [],
        "worker_policy_enforced": true
      }
    ]
  },
  "duplicate_analysis": [
    {
      "group_size": 3,
      "group_total_bytes": 29067,
      "mirror_family": "fadhilweblib-mirror",
      "recommended_keep": "library/fadhilweblib/styles/theme.css",
      "safe_delete_candidates": [],
      "items": [
        {
          "path": "library/fadhilweblib/styles/theme.css",
          "size_bytes": 9689,
          "reference_count_exact_path": 4,
          "reference_count_basename": 15,
          "in_active_scope": true,
          "safe_delete_candidate": false,
          "is_recommended_keep": true
        },
        {
          "path": "website/home/theme.css",
          "size_bytes": 9689,
          "reference_count_exact_path": 2,
          "reference_count_basename": 15,
          "in_active_scope": true,
          "safe_delete_candidate": false,
          "is_recommended_keep": false
        },
        {
          "path": "website/website/mindmapmaker/theme.css",
          "size_bytes": 9689,
          "reference_count_exact_path": 2,
          "reference_count_basename": 15,
          "in_active_scope": true,
          "safe_delete_candidate": false,
          "is_recommended_keep": false
        }
      ]
    },
    {
      "group_size": 2,
      "group_total_bytes": 3974,
      "mirror_family": "fadhilweblib-mirror",
      "recommended_keep": "library/fadhilweblib/components/layout/surface.tsx",
      "safe_delete_candidates": [],
      "items": [
        {
          "path": "library/fadhilweblib/components/layout/surface.tsx",
          "size_bytes": 1987,
          "reference_count_exact_path": 4,
          "reference_count_basename": 6,
          "in_active_scope": true,
          "safe_delete_candidate": false,
          "is_recommended_keep": true
        },
        {
          "path": "website/mindmapmaker/src/lib/fadhilweblib/components/layout/surface.tsx",
          "size_bytes": 1987,
          "reference_count_exact_path": 2,
          "reference_count_basename": 6,
          "in_active_scope": true,
          "safe_delete_candidate": false,
          "is_recommended_keep": false
        }
      ]
    },
    {
      "group_size": 2,
      "group_total_bytes": 3858,
      "mirror_family": "fadhilweblib-mirror",
      "recommended_keep": "library/fadhilweblib/components/forms/range.tsx",
      "safe_delete_candidates": [],
      "items": [
        {
          "path": "library/fadhilweblib/components/forms/range.tsx",
          "size_bytes": 1929,
          "reference_count_exact_path": 4,
          "reference_count_basename": 6,
          "in_active_scope": true,
          "safe_delete_candidate": false,
          "is_recommended_keep": true
        },
        {
          "path": "website/mindmapmaker/src/lib/fadhilweblib/components/forms/range.tsx",
          "size_bytes": 1929,
          "reference_count_exact_path": 2,
          "reference_count_basename": 6,
          "in_active_scope": true,
          "safe_delete_candidate": false,
          "is_recommended_keep": false
        }
      ]
    },
    {
      "group_size": 2,
      "group_total_bytes": 3832,
      "mirror_family": "fadhilweblib-mirror",
      "recommended_keep": "library/fadhilweblib/components/navigation/breadcrumbs.tsx",
      "safe_delete_candidates": [],
      "items": [
        {
          "path": "library/fadhilweblib/components/navigation/breadcrumbs.tsx",
          "size_bytes": 1916,
          "reference_count_exact_path": 4,
          "reference_count_basename": 6,
          "in_active_scope": true,
          "safe_delete_candidate": false,
          "is_recommended_keep": true
        },
        {
          "path": "website/mindmapmaker/src/lib/fadhilweblib/components/navigation/breadcrumbs.tsx",
          "size_bytes": 1916,
          "reference_count_exact_path": 2,
          "reference_count_basename": 6,
          "in_active_scope": true,
          "safe_delete_candidate": false,
          "is_recommended_keep": false
        }
      ]
    },
    {
      "group_size": 2,
      "group_total_bytes": 3612,
      "mirror_family": "fadhilweblib-mirror",
      "recommended_keep": "library/fadhilweblib/core/use-stepper.ts",
      "safe_delete_candidates": [],
      "items": [
        {
          "path": "library/fadhilweblib/core/use-stepper.ts",
          "size_bytes": 1806,
          "reference_count_exact_path": 4,
          "reference_count_basename": 6,
          "in_active_scope": true,
          "safe_delete_candidate": false,
          "is_recommended_keep": true
        },
        {
          "path": "website/mindmapmaker/src/lib/fadhilweblib/core/use-stepper.ts",
          "size_bytes": 1806,
          "reference_count_exact_path": 2,
          "reference_count_basename": 6,
          "in_active_scope": true,
          "safe_delete_candidate": false,
          "is_recommended_keep": false
        }
      ]
    },
    {
      "group_size": 2,
      "group_total_bytes": 3604,
      "mirror_family": "fadhilweblib-mirror",
      "recommended_keep": "library/fadhilweblib/core/state-syntax-test.ts",
      "safe_delete_candidates": [],
      "items": [
        {
          "path": "library/fadhilweblib/core/state-syntax-test.ts",
          "size_bytes": 1802,
          "reference_count_exact_path": 4,
          "reference_count_basename": 6,
          "in_active_scope": true,
          "safe_delete_candidate": false,
          "is_recommended_keep": true
        },
        {
          "path": "website/mindmapmaker/src/lib/fadhilweblib/core/state-syntax-test.ts",
          "size_bytes": 1802,
          "reference_count_exact_path": 2,
          "reference_count_basename": 6,
          "in_active_scope": true,
          "safe_delete_candidate": false,
          "is_recommended_keep": false
        }
      ]
    },
    {
      "group_size": 2,
      "group_total_bytes": 3286,
      "mirror_family": "fadhilweblib-mirror",
      "recommended_keep": "library/fadhilweblib/components/forms/select.tsx",
      "safe_delete_candidates": [],
      "items": [
        {
          "path": "library/fadhilweblib/components/forms/select.tsx",
          "size_bytes": 1643,
          "reference_count_exact_path": 4,
          "reference_count_basename": 6,
          "in_active_scope": true,
          "safe_delete_candidate": false,
          "is_recommended_keep": true
        },
        {
          "path": "website/mindmapmaker/src/lib/fadhilweblib/components/forms/select.tsx",
          "size_bytes": 1643,
          "reference_count_exact_path": 2,
          "reference_count_basename": 6,
          "in_active_scope": true,
          "safe_delete_candidate": false,
          "is_recommended_keep": false
        }
      ]
    },
    {
      "group_size": 2,
      "group_total_bytes": 3264,
      "mirror_family": "fadhilweblib-mirror",
      "recommended_keep": "library/fadhilweblib/components/action-group.tsx",
      "safe_delete_candidates": [],
      "items": [
        {
          "path": "library/fadhilweblib/components/action-group.tsx",
          "size_bytes": 1632,
          "reference_count_exact_path": 4,
          "reference_count_basename": 6,
          "in_active_scope": true,
          "safe_delete_candidate": false,
          "is_recommended_keep": true
        },
        {
          "path": "website/mindmapmaker/src/lib/fadhilweblib/components/action-group.tsx",
          "size_bytes": 1632,
          "reference_count_exact_path": 2,
          "reference_count_basename": 6,
          "in_active_scope": true,
          "safe_delete_candidate": false,
          "is_recommended_keep": false
        }
      ]
    },
    {
      "group_size": 2,
      "group_total_bytes": 3226,
      "mirror_family": "fadhilweblib-mirror",
      "recommended_keep": "library/fadhilweblib/components/forms/textarea.tsx",
      "safe_delete_candidates": [],
      "items": [
        {
          "path": "library/fadhilweblib/components/forms/textarea.tsx",
          "size_bytes": 1613,
          "reference_count_exact_path": 4,
          "reference_count_basename": 6,
          "in_active_scope": true,
          "safe_delete_candidate": false,
          "is_recommended_keep": true
        },
        {
          "path": "website/mindmapmaker/src/lib/fadhilweblib/components/forms/textarea.tsx",
          "size_bytes": 1613,
          "reference_count_exact_path": 2,
          "reference_count_basename": 6,
          "in_active_scope": true,
          "safe_delete_candidate": false,
          "is_recommended_keep": false
        }
      ]
    },
    {
      "group_size": 2,
      "group_total_bytes": 3188,
      "mirror_family": "fadhilweblib-mirror",
      "recommended_keep": "library/fadhilweblib/components/layout/container.tsx",
      "safe_delete_candidates": [],
      "items": [
        {
          "path": "library/fadhilweblib/components/layout/container.tsx",
          "size_bytes": 1594,
          "reference_count_exact_path": 4,
          "reference_count_basename": 6,
          "in_active_scope": true,
          "safe_delete_candidate": false,
          "is_recommended_keep": true
        },
        {
          "path": "website/mindmapmaker/src/lib/fadhilweblib/components/layout/container.tsx",
          "size_bytes": 1594,
          "reference_count_exact_path": 2,
          "reference_count_basename": 6,
          "in_active_scope": true,
          "safe_delete_candidate": false,
          "is_recommended_keep": false
        }
      ]
    },
    {
      "group_size": 2,
      "group_total_bytes": 3180,
      "mirror_family": "fadhilweblib-mirror",
      "recommended_keep": "library/fadhilweblib/components/feedback/key-value-list.tsx",
      "safe_delete_candidates": [],
      "items": [
        {
          "path": "library/fadhilweblib/components/feedback/key-value-list.tsx",
          "size_bytes": 1590,
          "reference_count_exact_path": 4,
          "reference_count_basename": 6,
          "in_active_scope": true,
          "safe_delete_candidate": false,
          "is_recommended_keep": true
        },
        {
          "path": "website/mindmapmaker/src/lib/fadhilweblib/components/feedback/key-value-list.tsx",
          "size_bytes": 1590,
          "reference_count_exact_path": 2,
          "reference_count_basename": 6,
          "in_active_scope": true,
          "safe_delete_candidate": false,
          "is_recommended_keep": false
        }
      ]
    },
    {
      "group_size": 2,
      "group_total_bytes": 3162,
      "mirror_family": "fadhilweblib-mirror",
      "recommended_keep": "library/fadhilweblib/components/forms/input.tsx",
      "safe_delete_candidates": [],
      "items": [
        {
          "path": "library/fadhilweblib/components/forms/input.tsx",
          "size_bytes": 1581,
          "reference_count_exact_path": 4,
          "reference_count_basename": 6,
          "in_active_scope": true,
          "safe_delete_candidate": false,
          "is_recommended_keep": true
        },
        {
          "path": "website/mindmapmaker/src/lib/fadhilweblib/components/forms/input.tsx",
          "size_bytes": 1581,
          "reference_count_exact_path": 2,
          "reference_count_basename": 6,
          "in_active_scope": true,
          "safe_delete_candidate": false,
          "is_recommended_keep": false
        }
      ]
    },
    {
      "group_size": 2,
      "group_total_bytes": 2958,
      "mirror_family": "fadhilweblib-mirror",
      "recommended_keep": "library/fadhilweblib/core/dialog-test.ts",
      "safe_delete_candidates": [],
      "items": [
        {
          "path": "library/fadhilweblib/core/dialog-test.ts",
          "size_bytes": 1479,
          "reference_count_exact_path": 4,
          "reference_count_basename": 6,
          "in_active_scope": true,
          "safe_delete_candidate": false,
          "is_recommended_keep": true
        },
        {
          "path": "website/mindmapmaker/src/lib/fadhilweblib/core/dialog-test.ts",
          "size_bytes": 1479,
          "reference_count_exact_path": 2,
          "reference_count_basename": 6,
          "in_active_scope": true,
          "safe_delete_candidate": false,
          "is_recommended_keep": false
        }
      ]
    },
    {
      "group_size": 2,
      "group_total_bytes": 2892,
      "mirror_family": "fadhilweblib-mirror",
      "recommended_keep": "library/fadhilweblib/components/inline.tsx",
      "safe_delete_candidates": [],
      "items": [
        {
          "path": "library/fadhilweblib/components/inline.tsx",
          "size_bytes": 1446,
          "reference_count_exact_path": 4,
          "reference_count_basename": 6,
          "in_active_scope": true,
          "safe_delete_candidate": false,
          "is_recommended_keep": true
        },
        {
          "path": "website/mindmapmaker/src/lib/fadhilweblib/components/inline.tsx",
          "size_bytes": 1446,
          "reference_count_exact_path": 2,
          "reference_count_basename": 6,
          "in_active_scope": true,
          "safe_delete_candidate": false,
          "is_recommended_keep": false
        }
      ]
    },
    {
      "group_size": 2,
      "group_total_bytes": 2804,
      "mirror_family": "fadhilweblib-mirror",
      "recommended_keep": "library/fadhilweblib/core/roving-focus-test.ts",
      "safe_delete_candidates": [],
      "items": [
        {
          "path": "library/fadhilweblib/core/roving-focus-test.ts",
          "size_bytes": 1402,
          "reference_count_exact_path": 4,
          "reference_count_basename": 6,
          "in_active_scope": true,
          "safe_delete_candidate": false,
          "is_recommended_keep": true
        },
        {
          "path": "website/mindmapmaker/src/lib/fadhilweblib/core/roving-focus-test.ts",
          "size_bytes": 1402,
          "reference_count_exact_path": 2,
          "reference_count_basename": 6,
          "in_active_scope": true,
          "safe_delete_candidate": false,
          "is_recommended_keep": false
        }
      ]
    },
    {
      "group_size": 2,
      "group_total_bytes": 2634,
      "mirror_family": "fadhilweblib-mirror",
      "recommended_keep": "library/fadhilweblib/core/disclosure-test.ts",
      "safe_delete_candidates": [],
      "items": [
        {
          "path": "library/fadhilweblib/core/disclosure-test.ts",
          "size_bytes": 1317,
          "reference_count_exact_path": 4,
          "reference_count_basename": 6,
          "in_active_scope": true,
          "safe_delete_candidate": false,
          "is_recommended_keep": true
        },
        {
          "path": "website/mindmapmaker/src/lib/fadhilweblib/core/disclosure-test.ts",
          "size_bytes": 1317,
          "reference_count_exact_path": 2,
          "reference_count_basename": 6,
          "in_active_scope": true,
          "safe_delete_candidate": false,
          "is_recommended_keep": false
        }
      ]
    },
    {
      "group_size": 2,
      "group_total_bytes": 2370,
      "mirror_family": "fadhilweblib-mirror",
      "recommended_keep": "library/fadhilweblib/components/feedback/skeleton.tsx",
      "safe_delete_candidates": [],
      "items": [
        {
          "path": "library/fadhilweblib/components/feedback/skeleton.tsx",
          "size_bytes": 1185,
          "reference_count_exact_path": 4,
          "reference_count_basename": 6,
          "in_active_scope": true,
          "safe_delete_candidate": false,
          "is_recommended_keep": true
        },
        {
          "path": "website/mindmapmaker/src/lib/fadhilweblib/components/feedback/skeleton.tsx",
          "size_bytes": 1185,
          "reference_count_exact_path": 2,
          "reference_count_basename": 6,
          "in_active_scope": true,
          "safe_delete_candidate": false,
          "is_recommended_keep": false
        }
      ]
    },
    {
      "group_size": 2,
      "group_total_bytes": 2292,
      "mirror_family": "fadhilweblib-mirror",
      "recommended_keep": "library/fadhilweblib/components/stack.tsx",
      "safe_delete_candidates": [],
      "items": [
        {
          "path": "library/fadhilweblib/components/stack.tsx",
          "size_bytes": 1146,
          "reference_count_exact_path": 4,
          "reference_count_basename": 6,
          "in_active_scope": true,
          "safe_delete_candidate": false,
          "is_recommended_keep": true
        },
        {
          "path": "website/mindmapmaker/src/lib/fadhilweblib/components/stack.tsx",
          "size_bytes": 1146,
          "reference_count_exact_path": 2,
          "reference_count_basename": 6,
          "in_active_scope": true,
          "safe_delete_candidate": false,
          "is_recommended_keep": false
        }
      ]
    },
    {
      "group_size": 2,
      "group_total_bytes": 2126,
      "mirror_family": "fadhilweblib-mirror",
      "recommended_keep": "library/fadhilweblib/core/use-controllable-state.ts",
      "safe_delete_candidates": [],
      "items": [
        {
          "path": "library/fadhilweblib/core/use-controllable-state.ts",
          "size_bytes": 1063,
          "reference_count_exact_path": 4,
          "reference_count_basename": 6,
          "in_active_scope": true,
          "safe_delete_candidate": false,
          "is_recommended_keep": true
        },
        {
          "path": "website/mindmapmaker/src/lib/fadhilweblib/core/use-controllable-state.ts",
          "size_bytes": 1063,
          "reference_count_exact_path": 2,
          "reference_count_basename": 6,
          "in_active_scope": true,
          "safe_delete_candidate": false,
          "is_recommended_keep": false
        }
      ]
    },
    {
      "group_size": 2,
      "group_total_bytes": 2110,
      "mirror_family": "fadhilweblib-mirror",
      "recommended_keep": "library/fadhilweblib/components/header-shell-module.css",
      "safe_delete_candidates": [],
      "items": [
        {
          "path": "library/fadhilweblib/components/header-shell-module.css",
          "size_bytes": 1055,
          "reference_count_exact_path": 4,
          "reference_count_basename": 7,
          "in_active_scope": true,
          "safe_delete_candidate": false,
          "is_recommended_keep": true
        },
        {
          "path": "website/mindmapmaker/src/lib/fadhilweblib/components/header-shell-module.css",
          "size_bytes": 1055,
          "reference_count_exact_path": 2,
          "reference_count_basename": 7,
          "in_active_scope": true,
          "safe_delete_candidate": false,
          "is_recommended_keep": false
        }
      ]
    },
    {
      "group_size": 2,
      "group_total_bytes": 2022,
      "mirror_family": "fadhilweblib-mirror",
      "recommended_keep": "library/fadhilweblib/core/theme-scope-test.ts",
      "safe_delete_candidates": [],
      "items": [
        {
          "path": "library/fadhilweblib/core/theme-scope-test.ts",
          "size_bytes": 1011,
          "reference_count_exact_path": 4,
          "reference_count_basename": 6,
          "in_active_scope": true,
          "safe_delete_candidate": false,
          "is_recommended_keep": true
        },
        {
          "path": "website/mindmapmaker/src/lib/fadhilweblib/core/theme-scope-test.ts",
          "size_bytes": 1011,
          "reference_count_exact_path": 2,
          "reference_count_basename": 6,
          "in_active_scope": true,
          "safe_delete_candidate": false,
          "is_recommended_keep": false
        }
      ]
    },
    {
      "group_size": 3,
      "group_total_bytes": 1971,
      "mirror_family": "general",
      "recommended_keep": "website/assets/public/music1-fadhil.mp3",
      "safe_delete_candidates": [],
      "items": [
        {
          "path": "assets/music1-fadhil.mp3",
          "size_bytes": 657,
          "reference_count_exact_path": 4,
          "reference_count_basename": 11,
          "in_active_scope": false,
          "safe_delete_candidate": false,
          "is_recommended_keep": false
        },
        {
          "path": "assets/public/music1-fadhil.mp3",
          "size_bytes": 657,
          "reference_count_exact_path": 8,
          "reference_count_basename": 11,
          "in_active_scope": false,
          "safe_delete_candidate": false,
          "is_recommended_keep": false
        },
        {
          "path": "website/assets/public/music1-fadhil.mp3",
          "size_bytes": 657,
          "reference_count_exact_path": 4,
          "reference_count_basename": 11,
          "in_active_scope": true,
          "safe_delete_candidate": false,
          "is_recommended_keep": true
        }
      ]
    },
    {
      "group_size": 2,
      "group_total_bytes": 1934,
      "mirror_family": "fadhilweblib-mirror",
      "recommended_keep": "library/fadhilweblib/components/layout/section-module.css",
      "safe_delete_candidates": [],
      "items": [
        {
          "path": "library/fadhilweblib/components/layout/section-module.css",
          "size_bytes": 967,
          "reference_count_exact_path": 4,
          "reference_count_basename": 7,
          "in_active_scope": true,
          "safe_delete_candidate": false,
          "is_recommended_keep": true
        },
        {
          "path": "website/mindmapmaker/src/lib/fadhilweblib/components/layout/section-module.css",
          "size_bytes": 967,
          "reference_count_exact_path": 2,
          "reference_count_basename": 7,
          "in_active_scope": true,
          "safe_delete_candidate": false,
          "is_recommended_keep": false
        }
      ]
    },
    {
      "group_size": 2,
      "group_total_bytes": 1772,
      "mirror_family": "fadhilweblib-mirror",
      "recommended_keep": "library/fadhilweblib/components/layout-module.css",
      "safe_delete_candidates": [],
      "items": [
        {
          "path": "library/fadhilweblib/components/layout-module.css",
          "size_bytes": 886,
          "reference_count_exact_path": 4,
          "reference_count_basename": 10,
          "in_active_scope": true,
          "safe_delete_candidate": false,
          "is_recommended_keep": true
        },
        {
          "path": "website/mindmapmaker/src/lib/fadhilweblib/components/layout-module.css",
          "size_bytes": 886,
          "reference_count_exact_path": 2,
          "reference_count_basename": 10,
          "in_active_scope": true,
          "safe_delete_candidate": false,
          "is_recommended_keep": false
        }
      ]
    },
    {
      "group_size": 2,
      "group_total_bytes": 1708,
      "mirror_family": "fadhilweblib-mirror",
      "recommended_keep": "library/fadhilweblib/core/selection-test.ts",
      "safe_delete_candidates": [],
      "items": [
        {
          "path": "library/fadhilweblib/core/selection-test.ts",
          "size_bytes": 854,
          "reference_count_exact_path": 4,
          "reference_count_basename": 6,
          "in_active_scope": true,
          "safe_delete_candidate": false,
          "is_recommended_keep": true
        },
        {
          "path": "website/mindmapmaker/src/lib/fadhilweblib/core/selection-test.ts",
          "size_bytes": 854,
          "reference_count_exact_path": 2,
          "reference_count_basename": 6,
          "in_active_scope": true,
          "safe_delete_candidate": false,
          "is_recommended_keep": false
        }
      ]
    },
    {
      "group_size": 2,
      "group_total_bytes": 1532,
      "mirror_family": "fadhilweblib-mirror",
      "recommended_keep": "library/fadhilweblib/components/forms/field-module.css",
      "safe_delete_candidates": [],
      "items": [
        {
          "path": "library/fadhilweblib/components/forms/field-module.css",
          "size_bytes": 766,
          "reference_count_exact_path": 4,
          "reference_count_basename": 7,
          "in_active_scope": true,
          "safe_delete_candidate": false,
          "is_recommended_keep": true
        },
        {
          "path": "website/mindmapmaker/src/lib/fadhilweblib/components/forms/field-module.css",
          "size_bytes": 766,
          "reference_count_exact_path": 2,
          "reference_count_basename": 7,
          "in_active_scope": true,
          "safe_delete_candidate": false,
          "is_recommended_keep": false
        }
      ]
    },
    {
      "group_size": 2,
      "group_total_bytes": 1464,
      "mirror_family": "fadhilweblib-mirror",
      "recommended_keep": "library/fadhilweblib/components/action-group-module.css",
      "safe_delete_candidates": [],
      "items": [
        {
          "path": "library/fadhilweblib/components/action-group-module.css",
          "size_bytes": 732,
          "reference_count_exact_path": 4,
          "reference_count_basename": 8,
          "in_active_scope": true,
          "safe_delete_candidate": false,
          "is_recommended_keep": true
        },
        {
          "path": "website/mindmapmaker/src/lib/fadhilweblib/components/action-group-module.css",
          "size_bytes": 732,
          "reference_count_exact_path": 2,
          "reference_count_basename": 8,
          "in_active_scope": true,
          "safe_delete_candidate": false,
          "is_recommended_keep": false
        }
      ]
    },
    {
      "group_size": 2,
      "group_total_bytes": 1348,
      "mirror_family": "fadhilweblib-mirror",
      "recommended_keep": "library/fadhilweblib/core/stepper-test.ts",
      "safe_delete_candidates": [],
      "items": [
        {
          "path": "library/fadhilweblib/core/stepper-test.ts",
          "size_bytes": 674,
          "reference_count_exact_path": 4,
          "reference_count_basename": 6,
          "in_active_scope": true,
          "safe_delete_candidate": false,
          "is_recommended_keep": true
        },
        {
          "path": "website/mindmapmaker/src/lib/fadhilweblib/core/stepper-test.ts",
          "size_bytes": 674,
          "reference_count_exact_path": 2,
          "reference_count_basename": 6,
          "in_active_scope": true,
          "safe_delete_candidate": false,
          "is_recommended_keep": false
        }
      ]
    },
    {
      "group_size": 2,
      "group_total_bytes": 1240,
      "mirror_family": "fadhilweblib-mirror",
      "recommended_keep": "library/fadhilweblib/core/types/layout.ts",
      "safe_delete_candidates": [],
      "items": [
        {
          "path": "library/fadhilweblib/core/types/layout.ts",
          "size_bytes": 620,
          "reference_count_exact_path": 4,
          "reference_count_basename": 6,
          "in_active_scope": true,
          "safe_delete_candidate": false,
          "is_recommended_keep": true
        },
        {
          "path": "website/mindmapmaker/src/lib/fadhilweblib/core/types/layout.ts",
          "size_bytes": 620,
          "reference_count_exact_path": 2,
          "reference_count_basename": 6,
          "in_active_scope": true,
          "safe_delete_candidate": false,
          "is_recommended_keep": false
        }
      ]
    },
    {
      "group_size": 2,
      "group_total_bytes": 520,
      "mirror_family": "fadhilweblib-mirror",
      "recommended_keep": "library/fadhilweblib/core/cx-test.ts",
      "safe_delete_candidates": [],
      "items": [
        {
          "path": "library/fadhilweblib/core/cx-test.ts",
          "size_bytes": 260,
          "reference_count_exact_path": 4,
          "reference_count_basename": 6,
          "in_active_scope": true,
          "safe_delete_candidate": false,
          "is_recommended_keep": true
        },
        {
          "path": "website/mindmapmaker/src/lib/fadhilweblib/core/cx-test.ts",
          "size_bytes": 260,
          "reference_count_exact_path": 2,
          "reference_count_basename": 6,
          "in_active_scope": true,
          "safe_delete_candidate": false,
          "is_recommended_keep": false
        }
      ]
    }
  ],
  "static_unused_audit": {
    "summary": {
      "tracked_files": 0,
      "candidate_files": 0,
      "used_via_vercel_config": 0,
      "used_via_exact_references": 0,
      "potential_unused_files": 0
    },
    "potential_unused_by_extension": {},
    "potential_unused_files": [],
    "notes": [
      "Static-unused audit skipped because vercel.json routes/builds are unavailable in current repository topology.",
      "Worker-based routing should be audited from src/index.js mapping instead."
    ]
  },
  "vercel_target_audit": {
    "summary": {
      "route_target_issues": 0,
      "build_glob_issues": 0
    },
    "route_target_issues": [],
    "build_glob_issues": []
  },
  "crawl_support_audit": {
    "robots": {
      "status": 200,
      "time_ms": 65.1,
      "has_user_agent_wildcard": true,
      "has_sitemap_directive": true
    },
    "sitemap": {
      "status": 200,
      "time_ms": 70.5,
      "url_count": 12
    },
    "sitemap_urls": [
      "https://fadhil.dev/",
      "https://fadhil.dev/academia",
      "https://fadhil.dev/archives",
      "https://fadhil.dev/books",
      "https://fadhil.dev/books/editor",
      "https://fadhil.dev/daily-streak",
      "https://fadhil.dev/dreambusiness",
      "https://fadhil.dev/home",
      "https://fadhil.dev/hype",
      "https://fadhil.dev/mindmapmaker",
      "https://fadhil.dev/rpg",
      "https://fadhil.dev/shareideas"
    ],
    "audited_routes_missing_in_sitemap": [],
    "summary": {
      "robots_note": "user-agent-ok,sitemap-ok",
      "sitemap_note": "url-count=12",
      "sitemap_url_count": 12,
      "audited_route_not_in_sitemap_count": 0
    }
  },
  "local_crawl_audit": {
    "summary": {
      "robots_exists": true,
      "sitemap_exists": true,
      "robots_has_user_agent_wildcard": true,
      "robots_has_sitemap_directive": true,
      "sitemap_url_count": 12,
      "audited_route_not_in_sitemap_count": 0
    },
    "audited_routes_missing_in_sitemap": []
  },
  "loc_audit": {
    "summary": {
      "tracked_files_scanned": 458,
      "total_lines": 94095,
      "blank_lines": 7786,
      "comment_lines": 1849,
      "code_lines": 84460
    },
    "by_extension": {
      ".css": {
        "files": 60,
        "total": 10214,
        "blank": 1079,
        "comment": 1618,
        "code": 7517
      },
      ".html": {
        "files": 18,
        "total": 2257,
        "blank": 116,
        "comment": 7,
        "code": 2134
      },
      ".js": {
        "files": 33,
        "total": 19574,
        "blank": 1327,
        "comment": 73,
        "code": 18174
      },
      ".json": {
        "files": 10,
        "total": 9512,
        "blank": 0,
        "comment": 0,
        "code": 9512
      },
      ".jsonc": {
        "files": 1,
        "total": 17,
        "blank": 0,
        "comment": 0,
        "code": 17
      },
      ".mjs": {
        "files": 1,
        "total": 27,
        "blank": 5,
        "comment": 0,
        "code": 22
      },
      ".py": {
        "files": 2,
        "total": 1069,
        "blank": 145,
        "comment": 8,
        "code": 916
      },
      ".sh": {
        "files": 2,
        "total": 46,
        "blank": 11,
        "comment": 7,
        "code": 28
      },
      ".sql": {
        "files": 6,
        "total": 87,
        "blank": 10,
        "comment": 12,
        "code": 65
      },
      ".svg": {
        "files": 1,
        "total": 3,
        "blank": 0,
        "comment": 0,
        "code": 3
      },
      ".toml": {
        "files": 1,
        "total": 12,
        "blank": 1,
        "comment": 0,
        "code": 11
      },
      ".ts": {
        "files": 200,
        "total": 30230,
        "blank": 3352,
        "comment": 74,
        "code": 26804
      },
      ".tsx": {
        "files": 114,
        "total": 20901,
        "blank": 1727,
        "comment": 30,
        "code": 19144
      },
      ".txt": {
        "files": 1,
        "total": 20,
        "blank": 5,
        "comment": 1,
        "code": 14
      },
      ".xml": {
        "files": 1,
        "total": 63,
        "blank": 0,
        "comment": 0,
        "code": 63
      },
      "[no-ext]": {
        "files": 7,
        "total": 63,
        "blank": 8,
        "comment": 19,
        "code": 36
      }
    }
  },
  "deprecated_code_audit": {
    "summary": {
      "total_hits": 0,
      "files_with_hits": 0,
      "hits_by_pattern": {}
    },
    "hits": []
  }
}
